[
    {
        "name": "Matoya's Cave Locations",
        "children": [
            {
                "name": "",
                "sections": [
                    {
                        "ref": "Aldi Sea/Matoya's Cave/Chest 1"
                    }
                ],
                "map_locations":
                [
                    {
                        "map": "matoyas_cave",
                        "x": 40,
                        "y": 88
                    }
                ]
            },
            {
                "name": "",
                "sections": [
                    {
                        "ref": "Aldi Sea/Matoya's Cave/Chest 2"
                    }
                ],
                "map_locations":
                [
                    {
                        "map": "matoyas_cave",
                        "x": 40,
                        "y": 104
                    }
                ]
            },
            {
                "name": "",
                "sections": [
                    {
                        "ref": "Aldi Sea/Matoya's Cave/Chest 3"
                    }
                ],
                "map_locations":
                [
                    {
                        "map": "matoyas_cave",
                        "x": 40,
                        "y": 136
                    }
                ]
            },
            {
                "name": "",
                "sections": [
                    {
                        "ref": "Aldi Sea/Matoya's Cave/Matoya"
                    }
                ],
                "map_locations":
                [
                    {
                        "map": "matoyas_cave",
                        "x": 152,
                        "y": 37
                    }
                ]
            }
        ]
    }
]